mockafka/__init__.py
mockafka/admin_client.py
mockafka/aiokafka/__init__.py
mockafka/aiokafka/aiokafka_admin_client.py
mockafka/aiokafka/aiokafka_consumer.py
mockafka/aiokafka/aiokafka_producer.py
mockafka/broker_metadata.py
mockafka/cluster_metadata.py
mockafka/consumer.py
mockafka/decorators/__init__.py
mockafka/decorators/aconsumer.py
mockafka/decorators/aproducer.py
mockafka/decorators/asetup_kafka.py
mockafka/decorators/bulk_producer.py
mockafka/decorators/consumer.py
mockafka/decorators/producer.py
mockafka/decorators/setup_kafka.py
mockafka/decorators/typing.py
mockafka/kafka_store.py
mockafka/message.py
mockafka/partition_metadata.py
mockafka/producer.py
mockafka/py.typed
mockafka/topic_metadata.py
mockafka_py-0.2.3.dist-info/METADATA
mockafka_py-0.2.3.dist-info/WHEEL
mockafka_py-0.2.3.dist-info/licenses/LICENSE
mockafka_py-0.2.3.dist-info/RECORD
