Metadata-Version: 2.4
Name: mockafka-py
Version: 0.2.3
Summary: A mock library for confluent kafka
License-File: LICENSE
Author: alm0ra
Author-email: ali.mrd318@gmail.com
Requires-Python: >=3.8,<4.0
Classifier: Programming Language :: Python :: 3
Classifier: Programming Language :: Python :: 3.8
Classifier: Programming Language :: Python :: 3.9
Classifier: Programming Language :: Python :: 3.10
Classifier: Programming Language :: Python :: 3.11
Classifier: Programming Language :: Python :: 3.12
Classifier: Programming Language :: Python :: 3.13
Classifier: Programming Language :: Python :: 3.14
Classifier: Typing :: Typed
Requires-Dist: aiokafka (>=0.10,<0.13)
Requires-Dist: confluent-kafka (>=1.9.2)
Requires-Dist: typing-extensions (>=4.12.2,<5.0.0)
Project-URL: Documentation, https://mockafka-py.readthedocs.io/
Project-URL: Repository, https://github.com/alm0ra/mockafka-py
